ampx/__init__.py
ampx-0.0.1.dist-info/LICENSE
ampx-0.0.1.dist-info/METADATA
ampx-0.0.1.dist-info/WHEEL
ampx-0.0.1.dist-info/top_level.txt
ampx-0.0.1.dist-info/RECORD
