Metadata-Version: 2.1
Name: ampx
Version: 0.0.1
Summary: A Python package for prediction and design of antimicrobial peptides
Home-page: https://github.com/JinZhangLab/ampx
Author: J Zhang
Author-email: jzhang@chemoinfolab.com
Classifier: Programming Language :: Python :: 3
Classifier: License :: OSI Approved :: MIT License
Classifier: Operating System :: OS Independent
Requires-Python: >=3.6
License-File: LICENSE
